dataloader/__init__.py
dataloader/__version__.py
dataloader/dataloader.py
async_dataloader-0.0.1.dist-info/WHEEL
async_dataloader-0.0.1.dist-info/METADATA
async_dataloader-0.0.1.dist-info/RECORD
