Metadata-Version: 2.1
Name: async-dataloader
Version: 0.0.1
Summary: Asyncio Dataloader for GraphQL.
Home-page: https://github.com/syfun/async-dataloader
License: MIT
Author: syfun
Author-email: sunyu418@gmail.com
Requires-Python: >=3.7,<4.0
Classifier: License :: OSI Approved :: MIT License
Classifier: Programming Language :: Python :: 3
Classifier: Programming Language :: Python :: 3.7
Classifier: Programming Language :: Python :: 3.8
Requires-Dist: typing_extensions (>=3.7.4,<4.0.0); python_version < "3.8"
